eez_backup/__init__.py
eez_backup/__main__.py
eez_backup/base.py
eez_backup/cli.py
eez_backup/command.py
eez_backup/config.py
eez_backup/monitor.py
eez_backup/playground.py
eez_backup/profile.py
eez_backup/repository.py
eez_backup-0.4.0.dist-info/METADATA
eez_backup-0.4.0.dist-info/WHEEL
eez_backup-0.4.0.dist-info/entry_points.txt
eez_backup-0.4.0.dist-info/top_level.txt
eez_backup-0.4.0.dist-info/RECORD
