Metadata-Version: 2.4
Name: eez-backup
Version: 0.4.0
Summary: Another convenience wrapper for _restic_
Author-email: 0b11001111 <19192307+0b11001111@users.noreply.github.com>
License: MIT
Project-URL: homepage, https://github.com/0b11001111/eez-backup
Project-URL: repository, https://github.com/0b11001111/eez-backup
Keywords: backup,restic
Classifier: Topic :: System :: Archiving
Classifier: Topic :: System :: Archiving :: Backup
Classifier: Topic :: Utilities
Classifier: Typing :: Typed
Requires-Python: >=3.13
Requires-Dist: frozendict>=2.4.6
Requires-Dist: pydantic>=2.11.7
Requires-Dist: rich>=14.1.0
